bulk_ner/__init__.py
bulk_ner/annotate.py
bulk_ner/api.py
bulk_ner/src/__init__.py
bulk_ner/src/entity_indexed.py
bulk_ner/src/partitioning.py
bulk_ner/src/service_args.py
bulk_ner/src/service_dynamic.py
bulk_ner/src/service_prompt.py
bulk_ner/src/utils.py
bulk_ner/src/core/__init__.py
bulk_ner/src/core/bound.py
bulk_ner/src/core/entity.py
bulk_ner/src/ner/__init__.py
bulk_ner/src/ner/base.py
bulk_ner/src/ner/obj_desc.py
bulk_ner/src/pipeline/__init__.py
bulk_ner/src/pipeline/batching.py
bulk_ner/src/pipeline/context.py
bulk_ner/src/pipeline/entity_list.py
bulk_ner/src/pipeline/utils.py
bulk_ner/src/pipeline/item/__init__.py
bulk_ner/src/pipeline/item/base.py
bulk_ner/src/pipeline/item/merge.py
bulk_ner/src/pipeline/item/ner.py
bulk_ner-0.25.1.dist-info/LICENSE
bulk_ner-0.25.1.dist-info/METADATA
bulk_ner-0.25.1.dist-info/WHEEL
bulk_ner-0.25.1.dist-info/top_level.txt
bulk_ner-0.25.1.dist-info/RECORD
