Metadata-Version: 2.1
Name: bulk_ner
Version: 0.25.1
Summary: A no-strings inference implementation framework Named Entity Recognition (NER) service of wrapped AI models powered by AREkit and the related text-processing pipelines.
Home-page: https://github.com/nicolay-r/bulk-ner
Author: Nicolay Rusnachenko
Author-email: rusnicolay@gmail.com
License: MIT License
Keywords: natural language processing,named entity recognition,ner
Classifier: Programming Language :: Python
Classifier: Programming Language :: Python :: 3.9
Classifier: Topic :: Software Development :: Libraries :: Python Modules
Classifier: Topic :: Scientific/Engineering :: Information Analysis
Classifier: Topic :: Text Processing :: Linguistic
Requires-Python: >=3.6
License-File: LICENSE
